anglewrapper/__init__.py
anglewrapper/wrap.py
anglewrapper-0.1.1.dist-info/LICENSE
anglewrapper-0.1.1.dist-info/METADATA
anglewrapper-0.1.1.dist-info/WHEEL
anglewrapper-0.1.1.dist-info/top_level.txt
anglewrapper-0.1.1.dist-info/RECORD
