Metadata-Version: 2.1
Name: anglewrapper
Version: 0.1.1
Summary: A package for wrapping angles in radians and degrees
Author: James Brodovsky
License: MIT License
Project-URL: Homepage, https://github.com/jbrodovsky/angle_wrapper
Keywords: angle,wrapper,radians,degrees
Requires-Python: >=3.9
License-File: LICENSE
